Metadata-Version: 2.1
Name: simple-salesforce-tronok
Version: 0.77.3
Summary: A basic Salesforce.com REST API client with tweaks.
Home-page: https://github.com/tronok/simple-salesforce
Author: Dmitry Kalashnikov
Author-email: kalashnikovdm@gmail.com
Maintainer: Dmitry Kalashnikov
Maintainer-email: kalashnikovdm@gmail.com
License: Apache 2.0
Keywords: python salesforce salesforce.com
Platform: UNKNOWN
Classifier: Development Status :: 4 - Beta
Classifier: License :: OSI Approved :: Apache Software License
Classifier: Intended Audience :: Developers
Classifier: Intended Audience :: System Administrators
Classifier: Operating System :: OS Independent
Classifier: Topic :: Internet :: WWW/HTTP
Classifier: Programming Language :: Python :: 2.6
Classifier: Programming Language :: Python :: 2.7
Classifier: Programming Language :: Python :: 3.3
Classifier: Programming Language :: Python :: 3.4
Classifier: Programming Language :: Python :: 3.5
Classifier: Programming Language :: Python :: 3.6
Classifier: Programming Language :: Python :: Implementation :: PyPy
Requires-Dist: requests[security]
Requires-Dist: ijson (==2.4)
